{
  "docVersion": "1.0.0",
  "resource": {
    "name": "PGAFlagWorkflow",
    "kind": "package",
    "apiVersion": "orchestrator.uipath.com/v1",
    "projectKey": "f0aee031-18dd-4c5a-a237-50a7e4d021ec",
    "isOverridable": true,
    "dependencies": [],
    "runtimeDependencies": [],
    "folders": [
      {
        "fullyQualifiedName": "solution_folder"
      }
    ],
    "spec": {
      "name": "PGAFlagWorkflow"
    },
    "locks": [],
    "key": "23fa4960-eb38-4f34-b23b-1cb6f4257e87",
    "files": []
  }
}